one_driving/__init__.py
one_driving/workaround.py
ownershipworkaround-0.1.0.dist-info/LICENSE
ownershipworkaround-0.1.0.dist-info/METADATA
ownershipworkaround-0.1.0.dist-info/WHEEL
ownershipworkaround-0.1.0.dist-info/top_level.txt
ownershipworkaround-0.1.0.dist-info/RECORD
