Metadata-Version: 2.1
Name: ownershipworkaround
Version: 0.1.0
Summary: Only one object containing the iterator or closure, cloning and errors related to this concept
Author-email: Ammar Husain <ammar.s.husain@gmail.com>
Project-URL: Homepage, https://github.com/Cobord/OwnershipWorkaround
Project-URL: Bug Tracker, https://github.com/Cobord/OwnershipWorkaround/issues
Classifier: Programming Language :: Python :: 3
Classifier: License :: OSI Approved :: GNU General Public License v3 (GPLv3)
Requires-Python: >=3.12
License-File: LICENSE
